qvncwidget/__init__.py
qvncwidget/easystruct.py
qvncwidget/qvncwidget.py
qvncwidget/rfb.py
qvncwidget/rfbconstants.py
qvncwidget/rfbdes.py
qvncwidget/rfbhelpers.py
qvncwidget-0.3.5.dist-info/LICENSE
qvncwidget-0.3.5.dist-info/METADATA
qvncwidget-0.3.5.dist-info/WHEEL
qvncwidget-0.3.5.dist-info/RECORD
