Metadata-Version: 2.1
Name: QVncWidget
Version: 0.3.5
Summary: VNC QT Widget for Python using PyQt5
Home-page: https://github.com/zocker-160/pyQVNCWidget
License: GPLv3+
Author: zocker_160
Author-email: zocker1600@posteo.net
Requires-Python: >=3.7,<4.0
Classifier: License :: Other/Proprietary License
Classifier: Programming Language :: Python :: 3
Classifier: Programming Language :: Python :: 3.7
Classifier: Programming Language :: Python :: 3.8
Classifier: Programming Language :: Python :: 3.9
Classifier: Programming Language :: Python :: 3.10
Classifier: Programming Language :: Python :: 3.11
Classifier: Programming Language :: Python :: 3.12
Requires-Dist: PyQt5 (>=5.12.8,<6.0.0)
Requires-Dist: pyDes (>=2.0.1,<3.0.0)
Requires-Dist: service-identity (>=21.1.0,<22.0.0)
Project-URL: Repository, https://github.com/zocker-160/pyQVNCWidget
